{
    "dataFrom": "",
    "emptyFlag": false,
    "errorCode": "0",
    "errorMessage": "处理成功",
    "success": true,
    "value": {
        "vtoolsConfig": {
            "offLineSaleStatus": 1,
            "offLineStopMessage": "抱歉，本彩种已停止销售",
            "onLineSaleStatus": 1,
            "onLineStopMessage": "抱歉，本彩种已停止销售"
        },
        "matchInfoList": [
            {
                "businessDate": "2024-06-05",
                "subMatchList": [
                    {
                        "awayRank": "",
                        "awayTeamAbbEnName": "MNG",
                        "awayTeamAbbName": "黑山",
                        "awayTeamAllName": "黑山",
                        "awayTeamCode": "MNG",
                        "awayTeamId": 885,
                        "backColor": "005E5E",
                        "baseAwayTeamId": 0,
                        "baseHomeTeamId": 0,
                        "bettingAllUp": 0,
                        "bettingSingle": 0,
                        "businessDate": "2024-06-05",
                        "crs": {},
                        "groupName": "",
                        "had": {},
                        "hafu": {},
                        "hhad": {},
                        "homeRank": "",
                        "homeTeamAbbEnName": "BEG",
                        "homeTeamAbbName": "比利时",
                        "homeTeamAllName": "比利时",
                        "homeTeamCode": "BEG",
                        "homeTeamId": 363,
                        "isHide": 0,
                        "isHot": 0,
                        "leagueAbbName": "国际赛",
                        "leagueAllName": "国际赛",
                        "leagueCode": "INT",
                        "leagueId": 39,
                        "lineNum": "",
                        "matchDate": "2024-06-06",
                        "matchId": 1025646,
                        "matchName": "",
                        "matchNum": 3005,
                        "matchNumDate": "",
                        "matchNumStr": "周三005",
                        "matchStatus": "Selling",
                        "matchTime": "02:30:00",
                        "matchWeek": "周三",
                        "oddsList": [
                            {
                                "a": "",
                                "d": "",
                                "goalLine": "",
                                "goalLineF": "",
                                "goalLineValue": "",
                                "h": "",
                                "matchId": 0,
                                "matchNum": 0,
                                "odds": "",
                                "poolCode": "TTG",
                                "poolId": 1118354,
                                "updateDate": "2024-06-05",
                                "updateTime": "20:04:15"
                            }
                        ],
                        "poolList": [
                            {
                                "allUp": 1,
                                "bettingAllup": 1,
                                "bettingSingle": 1,
                                "cbtAllUp": 1,
                                "cbtSingle": 1,
                                "cbtValue": 1,
                                "fixedOddsgoalLine": "",
                                "intAllUp": 0,
                                "intSingle": 0,
                                "intValue": 2,
                                "matchId": 0,
                                "matchNum": 0,
                                "poolCloseDate": "",
                                "poolCloseTime": "",
                                "poolCode": "TTG",
                                "poolId": 1118354,
                                "poolOddsType": "F",
                                "poolStatus": "Selling",
                                "sellInitialDate": "",
                                "sellInitialTime": "",
                                "single": 1,
                                "updateDate": "",
                                "updateTime": "",
                                "vbtAllUp": 0,
                                "vbtSingle": 0,
                                "vbtValue": 0
                            }
                        ],
                        "remark": "",
                        "sellStatus": 1,
                        "taxDateNo": "",
                        "ttg": {
                            "goalLine": "",
                            "goalLineValue": "",
                            "s0": "22.00",
                            "s0f": "0",
                            "s1": "7.20",
                            "s1f": "0",
                            "s2": "4.50",
                            "s2f": "0",
                            "s3": "3.60",
                            "s3f": "1",
                            "s4": "4.30",
                            "s4f": "0",
                            "s5": "7.30",
                            "s5f": "-1",
                            "s6": "13.00",
                            "s6f": "-1",
                            "s7": "13.50",
                            "s7f": "-1",
                            "updateDate": "2024-06-05",
                            "updateTime": "20:04:15"
                        },
                        "vote": {}
                    }
                ],
                "weekday": "周三",
                "matchCount": 1,
                "matchNumDate": ""
            },
            {
                "businessDate": "2024-06-06",
                "subMatchList": [
                    {
                        "awayRank": "[Group F1]",
                        "awayTeamAbbEnName": "IRQ",
                        "awayTeamAbbName": "伊拉克",
                        "awayTeamAllName": "伊拉克",
                        "awayTeamCode": "IRQ",
                        "awayTeamId": 436,
                        "backColor": "660000",
                        "baseAwayTeamId": 0,
                        "baseHomeTeamId": 0,
                        "bettingAllUp": 0,
                        "bettingSingle": 0,
                        "businessDate": "2024-06-06",
                        "crs": {},
                        "groupName": "",
                        "had": {},
                        "hafu": {},
                        "hhad": {},
                        "homeRank": "[Group F2]",
                        "homeTeamAbbEnName": "INA",
                        "homeTeamAbbName": "印尼",
                        "homeTeamAllName": "印度尼西亚",
                        "homeTeamCode": "INA",
                        "homeTeamId": 429,
                        "isHide": 0,
                        "isHot": 0,
                        "leagueAbbName": "世预赛",
                        "leagueAllName": "世界杯预选赛",
                        "leagueCode": "WCQ",
                        "leagueId": 73,
                        "lineNum": "",
                        "matchDate": "2024-06-06",
                        "matchId": 1025647,
                        "matchName": "",
                        "matchNum": 4001,
                        "matchNumDate": "",
                        "matchNumStr": "周四001",
                        "matchStatus": "Selling",
                        "matchTime": "17:00:00",
                        "matchWeek": "周四",
                        "oddsList": [
                            {
                                "a": "",
                                "d": "",
                                "goalLine": "",
                                "goalLineF": "",
                                "goalLineValue": "",
                                "h": "",
                                "matchId": 0,
                                "matchNum": 0,
                                "odds": "",
                                "poolCode": "TTG",
                                "poolId": 1118350,
                                "updateDate": "2024-06-05",
                                "updateTime": "10:29:48"
                            }
                        ],
                        "poolList": [
                            {
                                "allUp": 1,
                                "bettingAllup": 1,
                                "bettingSingle": 1,
                                "cbtAllUp": 1,
                                "cbtSingle": 1,
                                "cbtValue": 1,
                                "fixedOddsgoalLine": "",
                                "intAllUp": 0,
                                "intSingle": 0,
                                "intValue": 2,
                                "matchId": 0,
                                "matchNum": 0,
                                "poolCloseDate": "",
                                "poolCloseTime": "",
                                "poolCode": "TTG",
                                "poolId": 1118350,
                                "poolOddsType": "F",
                                "poolStatus": "Selling",
                                "sellInitialDate": "",
                                "sellInitialTime": "",
                                "single": 1,
                                "updateDate": "",
                                "updateTime": "",
                                "vbtAllUp": 0,
                                "vbtSingle": 0,
                                "vbtValue": 0
                            }
                        ],
                        "remark": "",
                        "sellStatus": 1,
                        "taxDateNo": "",
                        "ttg": {
                            "goalLine": "",
                            "goalLineValue": "",
                            "s0": "9.00",
                            "s0f": "0",
                            "s1": "4.40",
                            "s1f": "0",
                            "s2": "3.40",
                            "s2f": "0",
                            "s3": "3.90",
                            "s3f": "0",
                            "s4": "6.25",
                            "s4f": "0",
                            "s5": "11.00",
                            "s5f": "0",
                            "s6": "25.00",
                            "s6f": "0",
                            "s7": "40.00",
                            "s7f": "0",
                            "updateDate": "2024-06-05",
                            "updateTime": "10:29:48"
                        },
                        "vote": {}
                    },
                    {
                        "awayRank": "[Group F4]",
                        "awayTeamAbbEnName": "PHP",
                        "awayTeamAbbName": "菲律宾",
                        "awayTeamAllName": "菲律宾",
                        "awayTeamCode": "PHP",
                        "awayTeamId": 1522,
                        "backColor": "660000",
                        "baseAwayTeamId": 0,
                        "baseHomeTeamId": 0,
                        "bettingAllUp": 0,
                        "bettingSingle": 0,
                        "businessDate": "2024-06-06",
                        "crs": {},
                        "groupName": "",
                        "had": {},
                        "hafu": {},
                        "hhad": {},
                        "homeRank": "[Group F3]",
                        "homeTeamAbbEnName": "VNM",
                        "homeTeamAbbName": "越南",
                        "homeTeamAllName": "越南",
                        "homeTeamCode": "VNM",
                        "homeTeamId": 926,
                        "isHide": 0,
                        "isHot": 0,
                        "leagueAbbName": "世预赛",
                        "leagueAllName": "世界杯预选赛",
                        "leagueCode": "WCQ",
                        "leagueId": 73,
                        "lineNum": "",
                        "matchDate": "2024-06-06",
                        "matchId": 1025648,
                        "matchName": "",
                        "matchNum": 4002,
                        "matchNumDate": "",
                        "matchNumStr": "周四002",
                        "matchStatus": "Selling",
                        "matchTime": "20:00:00",
                        "matchWeek": "周四",
                        "oddsList": [
                            {
                                "a": "",
                                "d": "",
                                "goalLine": "",
                                "goalLineF": "",
                                "goalLineValue": "",
                                "h": "",
                                "matchId": 0,
                                "matchNum": 0,
                                "odds": "",
                                "poolCode": "TTG",
                                "poolId": 1118360,
                                "updateDate": "2024-06-05",
                                "updateTime": "10:29:48"
                            }
                        ],
                        "poolList": [
                            {
                                "allUp": 1,
                                "bettingAllup": 1,
                                "bettingSingle": 1,
                                "cbtAllUp": 1,
                                "cbtSingle": 1,
                                "cbtValue": 1,
                                "fixedOddsgoalLine": "",
                                "intAllUp": 0,
                                "intSingle": 0,
                                "intValue": 2,
                                "matchId": 0,
                                "matchNum": 0,
                                "poolCloseDate": "",
                                "poolCloseTime": "",
                                "poolCode": "TTG",
                                "poolId": 1118360,
                                "poolOddsType": "F",
                                "poolStatus": "Selling",
                                "sellInitialDate": "",
                                "sellInitialTime": "",
                                "single": 1,
                                "updateDate": "",
                                "updateTime": "",
                                "vbtAllUp": 0,
                                "vbtSingle": 0,
                                "vbtValue": 0
                            }
                        ],
                        "remark": "",
                        "sellStatus": 1,
                        "taxDateNo": "",
                        "ttg": {
                            "goalLine": "",
                            "goalLineValue": "",
                            "s0": "14.00",
                            "s0f": "0",
                            "s1": "5.50",
                            "s1f": "0",
                            "s2": "3.70",
                            "s2f": "0",
                            "s3": "3.80",
                            "s3f": "0",
                            "s4": "5.15",
                            "s4f": "0",
                            "s5": "8.25",
                            "s5f": "0",
                            "s6": "16.00",
                            "s6f": "0",
                            "s7": "25.00",
                            "s7f": "0",
                            "updateDate": "2024-06-05",
                            "updateTime": "10:29:48"
                        },
                        "vote": {}
                    },
                    {
                        "awayRank": "[Group C3]",
                        "awayTeamAbbEnName": "THA",
                        "awayTeamAbbName": "泰国",
                        "awayTeamAllName": "泰国",
                        "awayTeamCode": "THA",
                        "awayTeamId": 441,
                        "backColor": "660000",
                        "baseAwayTeamId": 0,
                        "baseHomeTeamId": 0,
                        "bettingAllUp": 0,
                        "bettingSingle": 0,
                        "businessDate": "2024-06-06",
                        "crs": {},
                        "groupName": "",
                        "had": {},
                        "hafu": {},
                        "hhad": {},
                        "homeRank": "[Group C2]",
                        "homeTeamAbbEnName": "CHN",
                        "homeTeamAbbName": "中国",
                        "homeTeamAllName": "中国",
                        "homeTeamCode": "CHN",
                        "homeTeamId": 426,
                        "isHide": 0,
                        "isHot": 0,
                        "leagueAbbName": "世预赛",
                        "leagueAllName": "世界杯预选赛",
                        "leagueCode": "WCQ",
                        "leagueId": 73,
                        "lineNum": "",
                        "matchDate": "2024-06-06",
                        "matchId": 1025649,
                        "matchName": "",
                        "matchNum": 4003,
                        "matchNumDate": "",
                        "matchNumStr": "周四003",
                        "matchStatus": "Selling",
                        "matchTime": "20:00:00",
                        "matchWeek": "周四",
                        "oddsList": [
                            {
                                "a": "",
                                "d": "",
                                "goalLine": "",
                                "goalLineF": "",
                                "goalLineValue": "",
                                "h": "",
                                "matchId": 0,
                                "matchNum": 0,
                                "odds": "",
                                "poolCode": "TTG",
                                "poolId": 1118335,
                                "updateDate": "2024-06-05",
                                "updateTime": "10:29:48"
                            }
                        ],
                        "poolList": [
                            {
                                "allUp": 1,
                                "bettingAllup": 1,
                                "bettingSingle": 1,
                                "cbtAllUp": 1,
                                "cbtSingle": 1,
                                "cbtValue": 1,
                                "fixedOddsgoalLine": "",
                                "intAllUp": 0,
                                "intSingle": 0,
                                "intValue": 2,
                                "matchId": 0,
                                "matchNum": 0,
                                "poolCloseDate": "",
                                "poolCloseTime": "",
                                "poolCode": "TTG",
                                "poolId": 1118335,
                                "poolOddsType": "F",
                                "poolStatus": "Selling",
                                "sellInitialDate": "",
                                "sellInitialTime": "",
                                "single": 1,
                                "updateDate": "",
                                "updateTime": "",
                                "vbtAllUp": 0,
                                "vbtSingle": 0,
                                "vbtValue": 0
                            }
                        ],
                        "remark": "",
                        "sellStatus": 1,
                        "taxDateNo": "",
                        "ttg": {
                            "goalLine": "",
                            "goalLineValue": "",
                            "s0": "9.00",
                            "s0f": "0",
                            "s1": "4.40",
                            "s1f": "0",
                            "s2": "3.35",
                            "s2f": "0",
                            "s3": "3.95",
                            "s3f": "0",
                            "s4": "6.50",
                            "s4f": "0",
                            "s5": "11.00",
                            "s5f": "0",
                            "s6": "24.00",
                            "s6f": "0",
                            "s7": "38.00",
                            "s7f": "0",
                            "updateDate": "2024-06-05",
                            "updateTime": "10:29:48"
                        },
                        "vote": {}
                    },
                    {
                        "awayRank": "[Group C1]",
                        "awayTeamAbbEnName": "KOR",
                        "awayTeamAbbName": "韩国",
                        "awayTeamAllName": "韩国",
                        "awayTeamCode": "KOR",
                        "awayTeamId": 430,
                        "backColor": "660000",
                        "baseAwayTeamId": 0,
                        "baseHomeTeamId": 0,
                        "bettingAllUp": 0,
                        "bettingSingle": 0,
                        "businessDate": "2024-06-06",
                        "crs": {},
                        "groupName": "",
                        "had": {},
                        "hafu": {},
                        "hhad": {},
                        "homeRank": "[Group C4]",
                        "homeTeamAbbEnName": "SGP",
                        "homeTeamAbbName": "新加坡",
                        "homeTeamAllName": "新加坡",
                        "homeTeamCode": "SGP",
                        "homeTeamId": 917,
                        "isHide": 0,
                        "isHot": 0,
                        "leagueAbbName": "世预赛",
                        "leagueAllName": "世界杯预选赛",
                        "leagueCode": "WCQ",
                        "leagueId": 73,
                        "lineNum": "",
                        "matchDate": "2024-06-06",
                        "matchId": 1025650,
                        "matchName": "",
                        "matchNum": 4004,
                        "matchNumDate": "",
                        "matchNumStr": "周四004",
                        "matchStatus": "Selling",
                        "matchTime": "20:00:00",
                        "matchWeek": "周四",
                        "oddsList": [
                            {
                                "a": "",
                                "d": "",
                                "goalLine": "",
                                "goalLineF": "",
                                "goalLineValue": "",
                                "h": "",
                                "matchId": 0,
                                "matchNum": 0,
                                "odds": "",
                                "poolCode": "TTG",
                                "poolId": 1118338,
                                "updateDate": "2024-06-05",
                                "updateTime": "11:35:59"
                            }
                        ],
                        "poolList": [
                            {
                                "allUp": 1,
                                "bettingAllup": 1,
                                "bettingSingle": 1,
                                "cbtAllUp": 1,
                                "cbtSingle": 1,
                                "cbtValue": 1,
                                "fixedOddsgoalLine": "",
                                "intAllUp": 0,
                                "intSingle": 0,
                                "intValue": 2,
                                "matchId": 0,
                                "matchNum": 0,
                                "poolCloseDate": "",
                                "poolCloseTime": "",
                                "poolCode": "TTG",
                                "poolId": 1118338,
                                "poolOddsType": "F",
                                "poolStatus": "Selling",
                                "sellInitialDate": "",
                                "sellInitialTime": "",
                                "single": 1,
                                "updateDate": "",
                                "updateTime": "",
                                "vbtAllUp": 0,
                                "vbtSingle": 0,
                                "vbtValue": 0
                            }
                        ],
                        "remark": "",
                        "sellStatus": 1,
                        "taxDateNo": "",
                        "ttg": {
                            "goalLine": "",
                            "goalLineValue": "",
                            "s0": "50.00",
                            "s0f": "1",
                            "s1": "18.00",
                            "s1f": "1",
                            "s2": "7.00",
                            "s2f": "1",
                            "s3": "5.00",
                            "s3f": "1",
                            "s4": "4.60",
                            "s4f": "1",
                            "s5": "4.80",
                            "s5f": "-1",
                            "s6": "6.25",
                            "s6f": "-1",
                            "s7": "5.00",
                            "s7f": "-1",
                            "updateDate": "2024-06-05",
                            "updateTime": "11:35:59"
                        },
                        "vote": {}
                    },
                    {
                        "awayRank": "[Group E1]",
                        "awayTeamAbbEnName": "IRA",
                        "awayTeamAbbName": "伊朗",
                        "awayTeamAllName": "伊朗",
                        "awayTeamCode": "IRA",
                        "awayTeamId": 440,
                        "backColor": "660000",
                        "baseAwayTeamId": 0,
                        "baseHomeTeamId": 0,
                        "bettingAllUp": 0,
                        "bettingSingle": 0,
                        "businessDate": "2024-06-06",
                        "crs": {},
                        "groupName": "",
                        "had": {},
                        "hafu": {},
                        "hhad": {},
                        "homeRank": "[Group E4]",
                        "homeTeamAbbEnName": "HK5",
                        "homeTeamAbbName": "中国香港",
                        "homeTeamAllName": "中国香港",
                        "homeTeamCode": "HK5",
                        "homeTeamId": 1572,
                        "isHide": 0,
                        "isHot": 0,
                        "leagueAbbName": "世预赛",
                        "leagueAllName": "世界杯预选赛",
                        "leagueCode": "WCQ",
                        "leagueId": 73,
                        "lineNum": "",
                        "matchDate": "2024-06-06",
                        "matchId": 1025651,
                        "matchName": "",
                        "matchNum": 4005,
                        "matchNumDate": "",
                        "matchNumStr": "周四005",
                        "matchStatus": "Selling",
                        "matchTime": "20:00:00",
                        "matchWeek": "周四",
                        "oddsList": [
                            {
                                "a": "",
                                "d": "",
                                "goalLine": "",
                                "goalLineF": "",
                                "goalLineValue": "",
                                "h": "",
                                "matchId": 0,
                                "matchNum": 0,
                                "odds": "",
                                "poolCode": "TTG",
                                "poolId": 1118345,
                                "updateDate": "2024-06-05",
                                "updateTime": "12:31:33"
                            }
                        ],
                        "poolList": [
                            {
                                "allUp": 1,
                                "bettingAllup": 1,
                                "bettingSingle": 1,
                                "cbtAllUp": 1,
                                "cbtSingle": 1,
                                "cbtValue": 1,
                                "fixedOddsgoalLine": "",
                                "intAllUp": 0,
                                "intSingle": 0,
                                "intValue": 2,
                                "matchId": 0,
                                "matchNum": 0,
                                "poolCloseDate": "",
                                "poolCloseTime": "",
                                "poolCode": "TTG",
                                "poolId": 1118345,
                                "poolOddsType": "F",
                                "poolStatus": "Selling",
                                "sellInitialDate": "",
                                "sellInitialTime": "",
                                "single": 1,
                                "updateDate": "",
                                "updateTime": "",
                                "vbtAllUp": 0,
                                "vbtSingle": 0,
                                "vbtValue": 0
                            }
                        ],
                        "remark": "",
                        "sellStatus": 1,
                        "taxDateNo": "",
                        "ttg": {
                            "goalLine": "",
                            "goalLineValue": "",
                            "s0": "45.00",
                            "s0f": "1",
                            "s1": "10.00",
                            "s1f": "1",
                            "s2": "5.55",
                            "s2f": "1",
                            "s3": "4.30",
                            "s3f": "1",
                            "s4": "4.45",
                            "s4f": "1",
                            "s5": "5.25",
                            "s5f": "-1",
                            "s6": "8.00",
                            "s6f": "-1",
                            "s7": "7.75",
                            "s7f": "-1",
                            "updateDate": "2024-06-05",
                            "updateTime": "12:31:33"
                        },
                        "vote": {}
                    },
                    {
                        "awayRank": "[Group E3]",
                        "awayTeamAbbEnName": "TKM",
                        "awayTeamAbbName": "土库曼",
                        "awayTeamAllName": "土库曼斯坦",
                        "awayTeamCode": "TKM",
                        "awayTeamId": 435,
                        "backColor": "660000",
                        "baseAwayTeamId": 0,
                        "baseHomeTeamId": 0,
                        "bettingAllUp": 0,
                        "bettingSingle": 0,
                        "businessDate": "2024-06-06",
                        "crs": {},
                        "groupName": "",
                        "had": {},
                        "hafu": {},
                        "hhad": {},
                        "homeRank": "[Group E2]",
                        "homeTeamAbbEnName": "UZB",
                        "homeTeamAbbName": "乌兹别克",
                        "homeTeamAllName": "乌兹别克斯坦",
                        "homeTeamCode": "UZB",
                        "homeTeamId": 437,
                        "isHide": 0,
                        "isHot": 0,
                        "leagueAbbName": "世预赛",
                        "leagueAllName": "世界杯预选赛",
                        "leagueCode": "WCQ",
                        "leagueId": 73,
                        "lineNum": "",
                        "matchDate": "2024-06-06",
                        "matchId": 1025652,
                        "matchName": "",
                        "matchNum": 4006,
                        "matchNumDate": "",
                        "matchNumStr": "周四006",
                        "matchStatus": "Selling",
                        "matchTime": "22:30:00",
                        "matchWeek": "周四",
                        "oddsList": [
                            {
                                "a": "",
                                "d": "",
                                "goalLine": "",
                                "goalLineF": "",
                                "goalLineValue": "",
                                "h": "",
                                "matchId": 0,
                                "matchNum": 0,
                                "odds": "",
                                "poolCode": "TTG",
                                "poolId": 1118358,
                                "updateDate": "2024-06-05",
                                "updateTime": "10:29:48"
                            }
                        ],
                        "poolList": [
                            {
                                "allUp": 1,
                                "bettingAllup": 1,
                                "bettingSingle": 1,
                                "cbtAllUp": 1,
                                "cbtSingle": 1,
                                "cbtValue": 1,
                                "fixedOddsgoalLine": "",
                                "intAllUp": 0,
                                "intSingle": 0,
                                "intValue": 2,
                                "matchId": 0,
                                "matchNum": 0,
                                "poolCloseDate": "",
                                "poolCloseTime": "",
                                "poolCode": "TTG",
                                "poolId": 1118358,
                                "poolOddsType": "F",
                                "poolStatus": "Selling",
                                "sellInitialDate": "",
                                "sellInitialTime": "",
                                "single": 1,
                                "updateDate": "",
                                "updateTime": "",
                                "vbtAllUp": 0,
                                "vbtSingle": 0,
                                "vbtValue": 0
                            }
                        ],
                        "remark": "",
                        "sellStatus": 1,
                        "taxDateNo": "",
                        "ttg": {
                            "goalLine": "",
                            "goalLineValue": "",
                            "s0": "26.00",
                            "s0f": "0",
                            "s1": "8.00",
                            "s1f": "0",
                            "s2": "4.60",
                            "s2f": "0",
                            "s3": "3.80",
                            "s3f": "0",
                            "s4": "4.50",
                            "s4f": "0",
                            "s5": "6.60",
                            "s5f": "0",
                            "s6": "10.50",
                            "s6f": "0",
                            "s7": "11.00",
                            "s7f": "0",
                            "updateDate": "2024-06-05",
                            "updateTime": "10:29:48"
                        },
                        "vote": {}
                    },
                    {
                        "awayRank": "[Group D3]",
                        "awayTeamAbbEnName": "MYS",
                        "awayTeamAbbName": "马来西亚",
                        "awayTeamAllName": "马来西亚",
                        "awayTeamCode": "MYS",
                        "awayTeamId": 927,
                        "backColor": "660000",
                        "baseAwayTeamId": 0,
                        "baseHomeTeamId": 0,
                        "bettingAllUp": 0,
                        "bettingSingle": 0,
                        "businessDate": "2024-06-06",
                        "crs": {},
                        "groupName": "",
                        "had": {},
                        "hafu": {},
                        "hhad": {},
                        "homeRank": "[Group D1]",
                        "homeTeamAbbEnName": "KGZ",
                        "homeTeamAbbName": "吉尔吉斯",
                        "homeTeamAllName": "吉尔吉斯斯坦",
                        "homeTeamCode": "KGZ",
                        "homeTeamId": 1512,
                        "isHide": 0,
                        "isHot": 0,
                        "leagueAbbName": "世预赛",
                        "leagueAllName": "世界杯预选赛",
                        "leagueCode": "WCQ",
                        "leagueId": 73,
                        "lineNum": "",
                        "matchDate": "2024-06-06",
                        "matchId": 1025653,
                        "matchName": "",
                        "matchNum": 4007,
                        "matchNumDate": "",
                        "matchNumStr": "周四007",
                        "matchStatus": "Selling",
                        "matchTime": "23:00:00",
                        "matchWeek": "周四",
                        "oddsList": [
                            {
                                "a": "",
                                "d": "",
                                "goalLine": "",
                                "goalLineF": "",
                                "goalLineValue": "",
                                "h": "",
                                "matchId": 0,
                                "matchNum": 0,
                                "odds": "",
                                "poolCode": "TTG",
                                "poolId": 1118369,
                                "updateDate": "2024-06-05",
                                "updateTime": "10:29:48"
                            }
                        ],
                        "poolList": [
                            {
                                "allUp": 1,
                                "bettingAllup": 1,
                                "bettingSingle": 1,
                                "cbtAllUp": 1,
                                "cbtSingle": 1,
                                "cbtValue": 1,
                                "fixedOddsgoalLine": "",
                                "intAllUp": 0,
                                "intSingle": 0,
                                "intValue": 2,
                                "matchId": 0,
                                "matchNum": 0,
                                "poolCloseDate": "",
                                "poolCloseTime": "",
                                "poolCode": "TTG",
                                "poolId": 1118369,
                                "poolOddsType": "F",
                                "poolStatus": "Selling",
                                "sellInitialDate": "",
                                "sellInitialTime": "",
                                "single": 1,
                                "updateDate": "",
                                "updateTime": "",
                                "vbtAllUp": 0,
                                "vbtSingle": 0,
                                "vbtValue": 0
                            }
                        ],
                        "remark": "",
                        "sellStatus": 1,
                        "taxDateNo": "",
                        "ttg": {
                            "goalLine": "",
                            "goalLineValue": "",
                            "s0": "9.00",
                            "s0f": "0",
                            "s1": "4.60",
                            "s1f": "0",
                            "s2": "3.40",
                            "s2f": "0",
                            "s3": "4.00",
                            "s3f": "0",
                            "s4": "6.00",
                            "s4f": "0",
                            "s5": "11.00",
                            "s5f": "0",
                            "s6": "23.00",
                            "s6f": "0",
                            "s7": "32.00",
                            "s7f": "0",
                            "updateDate": "2024-06-05",
                            "updateTime": "10:29:48"
                        },
                        "vote": {}
                    },
                    {
                        "awayRank": "[Group G3]",
                        "awayTeamAbbEnName": "TJK",
                        "awayTeamAbbName": "塔吉克",
                        "awayTeamAllName": "塔吉克斯坦",
                        "awayTeamCode": "TJK",
                        "awayTeamId": 1611,
                        "backColor": "660000",
                        "baseAwayTeamId": 0,
                        "baseHomeTeamId": 0,
                        "bettingAllUp": 0,
                        "bettingSingle": 0,
                        "businessDate": "2024-06-06",
                        "crs": {},
                        "groupName": "",
                        "had": {},
                        "hafu": {},
                        "hhad": {},
                        "homeRank": "[Group G2]",
                        "homeTeamAbbEnName": "JOR",
                        "homeTeamAbbName": "约旦",
                        "homeTeamAllName": "约旦",
                        "homeTeamCode": "JOR",
                        "homeTeamId": 431,
                        "isHide": 0,
                        "isHot": 0,
                        "leagueAbbName": "世预赛",
                        "leagueAllName": "世界杯预选赛",
                        "leagueCode": "WCQ",
                        "leagueId": 73,
                        "lineNum": "",
                        "matchDate": "2024-06-07",
                        "matchId": 1025654,
                        "matchName": "",
                        "matchNum": 4008,
                        "matchNumDate": "",
                        "matchNumStr": "周四008",
                        "matchStatus": "Selling",
                        "matchTime": "01:30:00",
                        "matchWeek": "周四",
                        "oddsList": [
                            {
                                "a": "",
                                "d": "",
                                "goalLine": "",
                                "goalLineF": "",
                                "goalLineValue": "",
                                "h": "",
                                "matchId": 0,
                                "matchNum": 0,
                                "odds": "",
                                "poolCode": "TTG",
                                "poolId": 1118331,
                                "updateDate": "2024-06-05",
                                "updateTime": "10:29:48"
                            }
                        ],
                        "poolList": [
                            {
                                "allUp": 1,
                                "bettingAllup": 1,
                                "bettingSingle": 1,
                                "cbtAllUp": 1,
                                "cbtSingle": 1,
                                "cbtValue": 1,
                                "fixedOddsgoalLine": "",
                                "intAllUp": 0,
                                "intSingle": 0,
                                "intValue": 2,
                                "matchId": 0,
                                "matchNum": 0,
                                "poolCloseDate": "",
                                "poolCloseTime": "",
                                "poolCode": "TTG",
                                "poolId": 1118331,
                                "poolOddsType": "F",
                                "poolStatus": "Selling",
                                "sellInitialDate": "",
                                "sellInitialTime": "",
                                "single": 1,
                                "updateDate": "",
                                "updateTime": "",
                                "vbtAllUp": 0,
                                "vbtSingle": 0,
                                "vbtValue": 0
                            }
                        ],
                        "remark": "",
                        "sellStatus": 1,
                        "taxDateNo": "",
                        "ttg": {
                            "goalLine": "",
                            "goalLineValue": "",
                            "s0": "9.00",
                            "s0f": "0",
                            "s1": "4.30",
                            "s1f": "0",
                            "s2": "3.40",
                            "s2f": "0",
                            "s3": "3.95",
                            "s3f": "0",
                            "s4": "6.40",
                            "s4f": "0",
                            "s5": "11.50",
                            "s5f": "0",
                            "s6": "24.00",
                            "s6f": "0",
                            "s7": "38.00",
                            "s7f": "0",
                            "updateDate": "2024-06-05",
                            "updateTime": "10:29:48"
                        },
                        "vote": {}
                    }
                ],
                "weekday": "周四",
                "matchCount": 8,
                "matchNumDate": ""
            }
        ],
        "matchDateList": [
            {
                "businessDate": "2024-06-05",
                "businessDateCn": "周三",
                "matchDate": "",
                "matchDateCn": ""
            },
            {
                "businessDate": "2024-06-06",
                "businessDateCn": "周四",
                "matchDate": "",
                "matchDateCn": ""
            }
        ],
        "allUpList": {
            "TTG": [
                {
                    "fValue": 1,
                    "formula": "2x1",
                    "formulaType": 1,
                    "maxMatchCount": 0,
                    "poolCode": "TTG"
                },
                {
                    "fValue": 1,
                    "formula": "3x1",
                    "formulaType": 1,
                    "maxMatchCount": 0,
                    "poolCode": "TTG"
                },
                {
                    "fValue": 1,
                    "formula": "3x3",
                    "formulaType": 1,
                    "maxMatchCount": 0,
                    "poolCode": "TTG"
                },
                {
                    "fValue": 1,
                    "formula": "3x4",
                    "formulaType": 1,
                    "maxMatchCount": 0,
                    "poolCode": "TTG"
                },
                {
                    "fValue": 1,
                    "formula": "4x1",
                    "formulaType": 1,
                    "maxMatchCount": 0,
                    "poolCode": "TTG"
                },
                {
                    "fValue": 1,
                    "formula": "4x4",
                    "formulaType": 1,
                    "maxMatchCount": 0,
                    "poolCode": "TTG"
                },
                {
                    "fValue": 1,
                    "formula": "4x5",
                    "formulaType": 1,
                    "maxMatchCount": 0,
                    "poolCode": "TTG"
                },
                {
                    "fValue": 1,
                    "formula": "4x6",
                    "formulaType": 1,
                    "maxMatchCount": 0,
                    "poolCode": "TTG"
                },
                {
                    "fValue": 1,
                    "formula": "4x11",
                    "formulaType": 1,
                    "maxMatchCount": 0,
                    "poolCode": "TTG"
                },
                {
                    "fValue": 1,
                    "formula": "5x1",
                    "formulaType": 1,
                    "maxMatchCount": 0,
                    "poolCode": "TTG"
                },
                {
                    "fValue": 1,
                    "formula": "5x5",
                    "formulaType": 1,
                    "maxMatchCount": 0,
                    "poolCode": "TTG"
                },
                {
                    "fValue": 1,
                    "formula": "5x6",
                    "formulaType": 1,
                    "maxMatchCount": 0,
                    "poolCode": "TTG"
                },
                {
                    "fValue": 1,
                    "formula": "5x10",
                    "formulaType": 1,
                    "maxMatchCount": 0,
                    "poolCode": "TTG"
                },
                {
                    "fValue": 1,
                    "formula": "5x16",
                    "formulaType": 1,
                    "maxMatchCount": 0,
                    "poolCode": "TTG"
                },
                {
                    "fValue": 1,
                    "formula": "5x20",
                    "formulaType": 1,
                    "maxMatchCount": 0,
                    "poolCode": "TTG"
                },
                {
                    "fValue": 1,
                    "formula": "5x26",
                    "formulaType": 1,
                    "maxMatchCount": 0,
                    "poolCode": "TTG"
                },
                {
                    "fValue": 1,
                    "formula": "6x1",
                    "formulaType": 1,
                    "maxMatchCount": 0,
                    "poolCode": "TTG"
                },
                {
                    "fValue": 1,
                    "formula": "6x6",
                    "formulaType": 1,
                    "maxMatchCount": 0,
                    "poolCode": "TTG"
                },
                {
                    "fValue": 1,
                    "formula": "6x7",
                    "formulaType": 1,
                    "maxMatchCount": 0,
                    "poolCode": "TTG"
                },
                {
                    "fValue": 1,
                    "formula": "6x15",
                    "formulaType": 1,
                    "maxMatchCount": 0,
                    "poolCode": "TTG"
                },
                {
                    "fValue": 1,
                    "formula": "6x20",
                    "formulaType": 1,
                    "maxMatchCount": 0,
                    "poolCode": "TTG"
                },
                {
                    "fValue": 1,
                    "formula": "6x22",
                    "formulaType": 1,
                    "maxMatchCount": 0,
                    "poolCode": "TTG"
                },
                {
                    "fValue": 1,
                    "formula": "6x35",
                    "formulaType": 1,
                    "maxMatchCount": 0,
                    "poolCode": "TTG"
                },
                {
                    "fValue": 1,
                    "formula": "6x42",
                    "formulaType": 1,
                    "maxMatchCount": 0,
                    "poolCode": "TTG"
                },
                {
                    "fValue": 1,
                    "formula": "6x50",
                    "formulaType": 1,
                    "maxMatchCount": 0,
                    "poolCode": "TTG"
                },
                {
                    "fValue": 1,
                    "formula": "6x57",
                    "formulaType": 1,
                    "maxMatchCount": 0,
                    "poolCode": "TTG"
                },
                {
                    "fValue": 1,
                    "formula": "Single",
                    "formulaType": 1,
                    "maxMatchCount": 0,
                    "poolCode": "TTG"
                },
                {
                    "fValue": 1,
                    "formula": "2x1",
                    "formulaType": 2,
                    "maxMatchCount": 0,
                    "poolCode": "TTG"
                },
                {
                    "fValue": 1,
                    "formula": "3x1",
                    "formulaType": 2,
                    "maxMatchCount": 0,
                    "poolCode": "TTG"
                },
                {
                    "fValue": 1,
                    "formula": "4x1",
                    "formulaType": 2,
                    "maxMatchCount": 0,
                    "poolCode": "TTG"
                },
                {
                    "fValue": 1,
                    "formula": "5x1",
                    "formulaType": 2,
                    "maxMatchCount": 0,
                    "poolCode": "TTG"
                },
                {
                    "fValue": 1,
                    "formula": "6x1",
                    "formulaType": 2,
                    "maxMatchCount": 0,
                    "poolCode": "TTG"
                },
                {
                    "fValue": 1,
                    "formula": "Single",
                    "formulaType": 2,
                    "maxMatchCount": 0,
                    "poolCode": "TTG"
                }
            ]
        },
        "leagueList": [
            {
                "leagueId": "39",
                "leagueName": "国际赛",
                "leagueNameAbbr": "国际赛"
            },
            {
                "leagueId": "73",
                "leagueName": "世界杯预选赛",
                "leagueNameAbbr": "世预赛"
            }
        ],
        "totalCount": 9,
        "lastUpdateTime": "2024-06-05 20:04:15"
    }
}